klimapi_python/__init__.py
klimapi_python/api_client.py
klimapi_python/api_response.py
klimapi_python/configuration.py
klimapi_python/exceptions.py
klimapi_python/py.typed
klimapi_python/rest.py
klimapi_python/api/__init__.py
klimapi_python/api/klim_api.py
klimapi_python/models/__init__.py
klimapi_python/models/add_webhook_request.py
klimapi_python/models/bioenergy_average_energy.py
klimapi_python/models/bioenergy_average_volume.py
klimapi_python/models/bioenergy_average_weight.py
klimapi_python/models/bioenergy_biofuel_energy.py
klimapi_python/models/bioenergy_biofuel_volume.py
klimapi_python/models/bioenergy_biofuel_weight.py
klimapi_python/models/bioenergy_biogas_energy.py
klimapi_python/models/bioenergy_biogas_weight.py
klimapi_python/models/bioenergy_biomass_energy.py
klimapi_python/models/bioenergy_biomass_weight.py
klimapi_python/models/buy_amount.py
klimapi_python/models/buy_price.py
klimapi_python/models/calculate_request.py
klimapi_python/models/calculation_result.py
klimapi_python/models/calculation_results.py
klimapi_python/models/cart_item.py
klimapi_python/models/cart_result.py
klimapi_python/models/cart_result_calculation_results_inner.py
klimapi_python/models/cart_result_settings.py
klimapi_python/models/category.py
klimapi_python/models/certification_authority.py
klimapi_python/models/checkout_link.py
klimapi_python/models/checkout_link_calculated.py
klimapi_python/models/checkout_links.py
klimapi_python/models/checkout_links_calculated.py
klimapi_python/models/cloud_computing_average_cpu_hour.py
klimapi_python/models/cloud_computing_average_gb.py
klimapi_python/models/cloud_computing_average_gb_hour.py
klimapi_python/models/cloud_computing_average_tb_hour.py
klimapi_python/models/cloud_computing_cpu_cpu_hour.py
klimapi_python/models/cloud_computing_memory_gb_hour.py
klimapi_python/models/cloud_computing_network_gb.py
klimapi_python/models/cloud_computing_storage_tb_hour.py
klimapi_python/models/energy_consumption_average_energy.py
klimapi_python-1.1.29.dist-info/LICENSE
klimapi_python-1.1.29.dist-info/METADATA
klimapi_python-1.1.29.dist-info/WHEEL
klimapi_python-1.1.29.dist-info/top_level.txt
klimapi_python-1.1.29.dist-info/RECORD
