Metadata-Version: 2.1
Name: klimapi-python
Version: 1.1.29
Summary: KlimAPI - Calculation &amp; Compensation API
Home-page: https://github.com/KlimAPI/klimapi-python
Author: KlimAPI Team
Author-email: tech@klimapi.com
Keywords: klimapi
License-File: LICENSE
Requires-Dist: urllib3 <2.1.0,>=1.25.3
Requires-Dist: python-dateutil
Requires-Dist: pydantic >=2
Requires-Dist: typing-extensions >=4.7.1
